[ { "domain":"yfun.top","subject":"C=US; ST=California; L=San Francisco; O=Cloudflare, Inc.; CN=yfun.top","start":"Apr 13 00:00:00 2022 GMT","expire":"Apr 13 23:59:59 2023 GMT","issuer":"C=US; O=Cloudflare, Inc.; CN=Cloudflare Inc ECC CA-3","status":"即将失效","statuscolor":"warning","check":"2022-12-09 00:10:47","remain":"126"},{"domain":"www.yfun.top","subject":"C=US; ST=California; L=San Francisco; O=Cloudflare, Inc.; CN=www.yfun.top","start":"Apr 13 00:00:00 2022 GMT","expire":"Apr 13 23:59:59 2023 GMT","issuer":"C=US; O=Cloudflare, Inc.; CN=Cloudflare Inc ECC CA-3","status":"即将失效","statuscolor":"warning","check":"2022-12-09 00:10:48","remain":"126"},{"domain":"blog.yfun.top","subject":"C=US; ST=California; L=San Francisco; O=Cloudflare, Inc.; CN=blog.yfun.top","start":"Apr 18 00:00:00 2022 GMT","expire":"Apr 18 23:59:59 2023 GMT","issuer":"C=US; O=Cloudflare, Inc.; CN=Cloudflare Inc ECC CA-3","status":"即将失效","statuscolor":"warning","check":"2022-12-09 00:10:53","remain":"131"},{"domain":"ssl.yfun.top","subject":"C=US; ST=California; L=San Francisco; O=Cloudflare, Inc.; CN=sni.cloudflaressl.com","start":"Apr 22 00:00:00 2022 GMT","expire":"Apr 22 23:59:59 2023 GMT","issuer":"C=US; O=Cloudflare, Inc.; CN=Cloudflare Inc ECC CA-3","status":"即将失效","statuscolor":"warning","check":"2022-12-09 00:10:53","remain":"135"},{"domain":"cdn.yfun.top","subject":"C=US; ST=California; L=San Francisco; O=Cloudflare, Inc.; CN=cdn.yfun.top","start":"Apr 13 00:00:00 2022 GMT","expire":"Apr 13 23:59:59 2023 GMT","issuer":"C=US; O=Cloudflare, Inc.; CN=Cloudflare Inc ECC CA-3","status":"即将失效","statuscolor":"warning","check":"2022-12-09 00:10:54","remain":"126"},{"domain":"cfp.yfun.top","subject":"C=US; ST=California; L=San Francisco; O=Cloudflare, Inc.; CN=cfp.yfun.top","start":"May 31 00:00:00 2022 GMT","expire":"May 31 23:59:59 2023 GMT","issuer":"C=US; O=Cloudflare, Inc.; CN=Cloudflare Inc ECC CA-3","status":"无效","statuscolor":"error","check":"2022-12-09 00:10:54","remain":"174"},{"domain":"drive.yfun.top","subject":"CN=drive.yfun.top","start":"Oct 20 05:47:23 2022 GMT","expire":"Jan 18 05:47:22 2023 GMT","issuer":"C=US; O=Let's Encrypt; CN=R3","status":"无效","statuscolor":"error","check":"2022-12-09 00:10:55","remain":"40"},{"domain":"gdrive.yfun.top","subject":"C=US; ST=California; L=San Francisco; O=Cloudflare, Inc.; CN=sni.cloudflaressl.com","start":"Feb 2 00:00:00 2022 GMT","expire":"Feb 2 23:59:59 2023 GMT","issuer":"C=US; O=Cloudflare, Inc.; CN=Cloudflare Inc ECC CA-3","status":"无效","statuscolor":"error","check":"2022-12-09 00:10:55","remain":"56"},{"domain":"gravatar.yfun.top","subject":"C=US; ST=California; L=San Francisco; O=Cloudflare, Inc.; CN=sni.cloudflaressl.com","start":"Feb 2 00:00:00 2022 GMT","expire":"Feb 2 23:59:59 2023 GMT","issuer":"C=US; O=Cloudflare, Inc.; CN=Cloudflare Inc ECC CA-3","status":"无效","statuscolor":"error","check":"2022-12-09 00:10:56","remain":"56"},{"domain":"note.yfun.top","subject":"C=US; ST=California; L=San Francisco; O=Cloudflare, Inc.; CN=sni.cloudflaressl.com","start":"Apr 28 00:00:00 2022 GMT","expire":"Apr 28 23:59:59 2023 GMT","issuer":"C=US; O=Cloudflare, Inc.; CN=Cloudflare Inc ECC CA-3","status":"即将失效","statuscolor":"warning","check":"2022-12-09 00:10:57","remain":"141"},{"domain":"page.yfun.top","subject":"C=US; ST=California; L=San Francisco; O=Cloudflare, Inc.; CN=sni.cloudflaressl.com","start":"Feb 2 00:00:00 2022 GMT","expire":"Feb 2 23:59:59 2023 GMT","issuer":"C=US; O=Cloudflare, Inc.; CN=Cloudflare Inc ECC CA-3","status":"无效","statuscolor":"error","check":"2022-12-09 00:10:57","remain":"56"},{"domain":"t.yfun.top","subject":"C=US; ST=California; L=San Francisco; O=Cloudflare, Inc.; CN=sni.cloudflaressl.com","start":"Mar 1 00:00:00 2022 GMT","expire":"Mar 1 23:59:59 2023 GMT","issuer":"C=US; O=Cloudflare, Inc.; CN=Cloudflare Inc ECC CA-3","status":"无效","statuscolor":"error","check":"2022-12-09 00:10:57","remain":"83"},{"domain":"waline.blog.yfun.top","subject":"C=US; ST=California; L=San Francisco; O=Cloudflare, Inc.; CN=sni.cloudflaressl.com","start":"Jun 18 00:00:00 2022 GMT","expire":"Jun 18 23:59:59 2023 GMT","issuer":"C=US; O=Cloudflare, Inc.; CN=Cloudflare Inc ECC CA-3","status":"无效","statuscolor":"error","check":"2022-12-09 00:11:01","remain":"192"},{"domain":"twikoo.blog.yfun.top","subject":"CN=twikoo.blog.yfun.top","start":"Oct 11 09:22:39 2022 GMT","expire":"Jan 9 09:22:38 2023 GMT","issuer":"C=US; O=Let's Encrypt; CN=R3","status":"无效","statuscolor":"error","check":"2022-12-09 00:11:04","remain":"31"},{"domain":"proxy.yfun.top","subject":"C=US; ST=California; L=San Francisco; O=Cloudflare, Inc.; CN=sni.cloudflaressl.com","start":"Feb 2 00:00:00 2022 GMT","expire":"Feb 2 23:59:59 2023 GMT","issuer":"C=US; O=Cloudflare, Inc.; CN=Cloudflare Inc ECC CA-3","status":"无效","statuscolor":"error","check":"2022-12-09 00:11:05","remain":"56"},{"domain":"github.yfun.top","subject":"CN=github.yfun.top","start":"Oct 14 05:16:17 2022 GMT","expire":"Jan 12 05:16:16 2023 GMT","issuer":"C=US; O=Let's Encrypt; CN=R3","status":"无效","statuscolor":"error","check":"2022-12-09 00:11:06","remain":"34"},{"domain":"dqjs-proxy.vercel.app","subject":"CN=*.vercel.app","start":"Nov 26 10:28:57 2022 GMT","expire":"Feb 24 10:28:56 2023 GMT","issuer":"C=US; O=Let's Encrypt; CN=R3","status":"无效","statuscolor":"error","check":"2022-12-09 00:11:06","remain":"77"},{"domain":"hifun.js.org","subject":"CN=*.js.org","start":"Nov 7 04:02:47 2022 GMT","expire":"Feb 5 04:02:46 2023 GMT","issuer":"C=US; O=Let's Encrypt; CN=R3","status":"无效","statuscolor":"error","check":"2022-12-09 00:11:07","remain":"58"},{"domain":"start.yfun.top","subject":"CN=start.yfun.top","start":"Nov 4 13:24:46 2022 GMT","expire":"Feb 2 13:24:45 2023 GMT","issuer":"C=US; O=Let's Encrypt; CN=R3","status":"无效","statuscolor":"error","check":"2022-12-09 00:11:07","remain":"55"},{"domain":"cky.ink","subject":"","start":"","expire":"","issuer":"","status":"失效","statuscolor":"error","check":"2022-12-09 00:11:08","remain":"0" } ]
