[ { "domain":"yfun.top","subject":"C=US; ST=California; L=San Francisco; O=Cloudflare, Inc.; CN=yfun.top","start":"Apr 13 00:00:00 2022 GMT","expire":"Apr 13 23:59:59 2023 GMT","issuer":"C=US; O=Cloudflare, Inc.; CN=Cloudflare Inc ECC CA-3","status":"有效","statuscolor":"success","check":"2022-05-31 00:12:03","remain":"318"},{"domain":"www.yfun.top","subject":"C=US; ST=California; L=San Francisco; O=Cloudflare, Inc.; CN=www.yfun.top","start":"Apr 13 00:00:00 2022 GMT","expire":"Apr 13 23:59:59 2023 GMT","issuer":"C=US; O=Cloudflare, Inc.; CN=Cloudflare Inc ECC CA-3","status":"有效","statuscolor":"success","check":"2022-05-31 00:12:04","remain":"318"},{"domain":"blog.yfun.top","subject":"C=US; ST=California; L=San Francisco; O=Cloudflare, Inc.; CN=blog.yfun.top","start":"Apr 18 00:00:00 2022 GMT","expire":"Apr 18 23:59:59 2023 GMT","issuer":"C=US; O=Cloudflare, Inc.; CN=Cloudflare Inc ECC CA-3","status":"有效","statuscolor":"success","check":"2022-05-31 00:12:05","remain":"323"},{"domain":"ssl.yfun.top","subject":"C=US; ST=California; L=San Francisco; O=Cloudflare, Inc.; CN=sni.cloudflaressl.com","start":"Apr 22 00:00:00 2022 GMT","expire":"Apr 22 23:59:59 2023 GMT","issuer":"C=US; O=Cloudflare, Inc.; CN=Cloudflare Inc ECC CA-3","status":"有效","statuscolor":"success","check":"2022-05-31 00:12:05","remain":"327"},{"domain":"cdn.yfun.top","subject":"C=US; ST=California; L=San Francisco; O=Cloudflare, Inc.; CN=cdn.yfun.top","start":"Apr 13 00:00:00 2022 GMT","expire":"Apr 13 23:59:59 2023 GMT","issuer":"C=US; O=Cloudflare, Inc.; CN=Cloudflare Inc ECC CA-3","status":"有效","statuscolor":"success","check":"2022-05-31 00:12:06","remain":"318"},{"domain":"cfp.yfun.top","subject":"C=US; ST=California; L=San Francisco; O=Cloudflare, Inc.; CN=cfp.yfun.top","start":"Jul 1 00:00:00 2021 GMT","expire":"Jun 30 23:59:59 2022 GMT","issuer":"C=US; O=Cloudflare, Inc.; CN=Cloudflare Inc ECC CA-3","status":"有效","statuscolor":"success","check":"2022-05-31 00:12:06","remain":"31"},{"domain":"drive.yfun.top","subject":"CN=drive.yfun.top","start":"Mar 31 15:06:36 2022 GMT","expire":"Jun 29 15:06:35 2022 GMT","issuer":"C=US; O=Let's Encrypt; CN=R3","status":"有效","statuscolor":"success","check":"2022-05-31 00:12:07","remain":"29"},{"domain":"gdrive.yfun.top","subject":"C=US; ST=California; L=San Francisco; O=Cloudflare, Inc.; CN=sni.cloudflaressl.com","start":"Feb 2 00:00:00 2022 GMT","expire":"Feb 2 23:59:59 2023 GMT","issuer":"C=US; O=Cloudflare, Inc.; CN=Cloudflare Inc ECC CA-3","status":"有效","statuscolor":"success","check":"2022-05-31 00:12:07","remain":"248"},{"domain":"gravatar.yfun.top","subject":"C=US; ST=California; L=San Francisco; O=Cloudflare, Inc.; CN=sni.cloudflaressl.com","start":"Feb 2 00:00:00 2022 GMT","expire":"Feb 2 23:59:59 2023 GMT","issuer":"C=US; O=Cloudflare, Inc.; CN=Cloudflare Inc ECC CA-3","status":"有效","statuscolor":"success","check":"2022-05-31 00:12:09","remain":"248"},{"domain":"note.yfun.top","subject":"C=US; ST=California; L=San Francisco; O=Cloudflare, Inc.; CN=sni.cloudflaressl.com","start":"Apr 28 00:00:00 2022 GMT","expire":"Apr 28 23:59:59 2023 GMT","issuer":"C=US; O=Cloudflare, Inc.; CN=Cloudflare Inc ECC CA-3","status":"有效","statuscolor":"success","check":"2022-05-31 00:12:09","remain":"333"},{"domain":"page.yfun.top","subject":"C=US; ST=California; L=San Francisco; O=Cloudflare, Inc.; CN=sni.cloudflaressl.com","start":"Feb 2 00:00:00 2022 GMT","expire":"Feb 2 23:59:59 2023 GMT","issuer":"C=US; O=Cloudflare, Inc.; CN=Cloudflare Inc ECC CA-3","status":"有效","statuscolor":"success","check":"2022-05-31 00:12:09","remain":"248"},{"domain":"t.yfun.top","subject":"C=US; ST=California; L=San Francisco; O=Cloudflare, Inc.; CN=sni.cloudflaressl.com","start":"Mar 1 00:00:00 2022 GMT","expire":"Mar 1 23:59:59 2023 GMT","issuer":"C=US; O=Cloudflare, Inc.; CN=Cloudflare Inc ECC CA-3","status":"有效","statuscolor":"success","check":"2022-05-31 00:12:09","remain":"275"},{"domain":"waline.blog.yfun.top","subject":"C=US; ST=California; L=San Francisco; O=Cloudflare, Inc.; CN=sni.cloudflaressl.com","start":"Jul 19 00:00:00 2021 GMT","expire":"Jul 18 23:59:59 2022 GMT","issuer":"C=US; O=Cloudflare, Inc.; CN=Cloudflare Inc ECC CA-3","status":"有效","statuscolor":"success","check":"2022-05-31 00:12:13","remain":"49"},{"domain":"twikoo.blog.yfun.top","subject":"CN=twikoo.blog.yfun.top","start":"May 25 09:17:30 2022 GMT","expire":"Aug 23 09:17:29 2022 GMT","issuer":"C=US; O=Let's Encrypt; CN=R3","status":"有效","statuscolor":"success","check":"2022-05-31 00:12:17","remain":"84"},{"domain":"proxy.yfun.top","subject":"C=US; ST=California; L=San Francisco; O=Cloudflare, Inc.; CN=sni.cloudflaressl.com","start":"Feb 2 00:00:00 2022 GMT","expire":"Feb 2 23:59:59 2023 GMT","issuer":"C=US; O=Cloudflare, Inc.; CN=Cloudflare Inc ECC CA-3","status":"有效","statuscolor":"success","check":"2022-05-31 00:12:17","remain":"248"},{"domain":"github.yfun.top","subject":"CN=github.yfun.top","start":"May 26 09:57:04 2022 GMT","expire":"Aug 24 09:57:03 2022 GMT","issuer":"C=US; O=Let's Encrypt; CN=R3","status":"有效","statuscolor":"success","check":"2022-05-31 00:12:18","remain":"85"},{"domain":"dqjs-proxy.vercel.app","subject":"CN=*.vercel.app","start":"May 7 00:11:55 2022 GMT","expire":"Aug 5 00:11:54 2022 GMT","issuer":"C=US; O=Let's Encrypt; CN=R3","status":"有效","statuscolor":"success","check":"2022-05-31 00:12:18","remain":"66"},{"domain":"hifun.js.org","subject":"CN=*.js.org","start":"May 11 03:02:46 2022 GMT","expire":"Aug 9 03:02:45 2022 GMT","issuer":"C=US; O=Let's Encrypt; CN=R3","status":"有效","statuscolor":"success","check":"2022-05-31 00:12:18","remain":"70"},{"domain":"start.yfun.top","subject":"CN=start.yfun.top","start":"Apr 15 11:03:58 2022 GMT","expire":"Jul 14 11:03:57 2022 GMT","issuer":"C=US; O=Let's Encrypt; CN=R3","status":"有效","statuscolor":"success","check":"2022-05-31 00:12:19","remain":"44"},{"domain":"cky.ink","subject":"CN=cky.ink","start":"Apr 27 13:19:40 2022 GMT","expire":"Jul 26 13:19:39 2022 GMT","issuer":"C=US; O=Let's Encrypt; CN=R3","status":"有效","statuscolor":"success","check":"2022-05-31 00:12:20","remain":"56" } ]
